collector_optimisation/__init__.py
collector_optimisation/__main__.py
collector_optimisation/__utils__.py
collector_optimisation/bayesian_optimiser.py
collector_optimisation/model_wrapper.py
scdo-0.0.1.dist-info/LICENSE
scdo-0.0.1.dist-info/METADATA
scdo-0.0.1.dist-info/WHEEL
scdo-0.0.1.dist-info/entry_points.txt
scdo-0.0.1.dist-info/top_level.txt
scdo-0.0.1.dist-info/RECORD
